nqsdk/__init__.py
nqsdk/abstract/__init__.py
nqsdk/abstract/callback.py
nqsdk/abstract/channel.py
nqsdk/abstract/message.py
nqsdk/abstract/mixins.py
nqsdk/abstract/provider.py
nqsdk/abstract/quotas.py
nqsdk/consts.py
nqsdk/dummy/__init__.py
nqsdk/dummy/callback.py
nqsdk/dummy/message.py
nqsdk/dummy/provider.py
nqsdk/dummy/quotas.py
nqsdk/dummy/resources/config_schema.json
nqsdk/enums.py
nqsdk/exceptions.py
nqsdk/validation/__init__.py
nqsdk/validation/external_ids.py
nqsdk-1.0.0a16.dist-info/LICENSE
nqsdk-1.0.0a16.dist-info/METADATA
nqsdk-1.0.0a16.dist-info/WHEEL
nqsdk-1.0.0a16.dist-info/RECORD
