Metadata-Version: 2.1
Name: nqsdk
Version: 1.0.0a16
Summary: NQ SDK
Author: Inqana Ltd.
Author-email: develop@inqana.com
Requires-Python: >=3.10,<4.0
Classifier: Development Status :: 3 - Alpha
Classifier: Intended Audience :: Developers
Classifier: License :: OSI Approved :: Apache Software License
Classifier: Operating System :: OS Independent
Classifier: Programming Language :: Python :: 3
Classifier: Programming Language :: Python :: 3.10
Classifier: Programming Language :: Python :: 3.11
Requires-Dist: djangorestframework (>=3,<4)
Requires-Dist: email-validator (>=1,<2)
Requires-Dist: jsonschema (>=4,<5)
Requires-Dist: phonenumbers (>=8,<9)
Requires-Dist: pytz
Requires-Dist: requests (>=2,<3)
